bloxnickgenerator/__init__.py
bloxnickgenerator/generator.py
bloxnickgenerator-0.1.2.dist-info/LICENSE
bloxnickgenerator-0.1.2.dist-info/METADATA
bloxnickgenerator-0.1.2.dist-info/WHEEL
bloxnickgenerator-0.1.2.dist-info/top_level.txt
bloxnickgenerator-0.1.2.dist-info/RECORD
