Metadata-Version: 2.1
Name: bloxnickgenerator
Version: 0.1.2
Summary: A simple nickname generator for Roblox
Home-page: https://github.com/realkayo/Roblox-Nickname-Generator
Author: Kayon
Author-email: kayop621@gmail.com
Classifier: Programming Language :: Python :: 3
Classifier: License :: OSI Approved :: MIT License
Classifier: Operating System :: OS Independent
Requires-Python: >=3.6
License-File: LICENSE
Requires-Dist: requests
Requires-Dist: Faker
